dixit/__init__.py
dixit/chat.py
dixit/codes.py
dixit/config.json
dixit/config.py
dixit/core.py
dixit/deck.py
dixit/display.py
dixit/server.py
dixit/users.py
dixit/utils.py
dixit/static/favicon.ico
dixit/static/cards/dixit/README.txt
dixit/static/css/admin.css
dixit/static/css/magnifier.css
dixit/static/images/arrow.ico
dixit/static/images/banner.png
dixit/static/images/bunnyicongreen.png
dixit/static/images/bunnyicongrey.png
dixit/static/images/bunnyiconyellow.png
dixit/static/images/bunnyready.png
dixit/static/images/bunnyrun.png
dixit/static/images/cardback.png
dixit/static/images/thinking.gif
dixit/static/images/votetoken.png
dixit/static/images/smilies/Angry.png
dixit/static/images/smilies/Balloon.png
dixit/static/images/smilies/Big-Grin.png
dixit/static/images/smilies/Bomb.png
dixit/static/images/smilies/Broken-Heart.png
dixit/static/images/smilies/Bunny.png
dixit/static/images/smilies/Cake.png
dixit/static/images/smilies/Cat.png
dixit/static/images/smilies/Clock.png
dixit/static/images/smilies/Clown.png
dixit/static/images/smilies/Cold.png
dixit/static/images/smilies/Confused.png
dixit/static/images/smilies/Cool.png
dixit/static/images/smilies/Crying.png
dixit/static/images/smilies/Crying2.png
dixit/static/images/smilies/Dead.png
dixit/static/images/smilies/Devil.png
dixit/static/images/smilies/Dizzy.png
dixit/static/images/smilies/Dog.png
dixit/static/images/smilies/Don't-tell-Anyone.png
dixit/static/images/smilies/Drinks.png
dixit/static/images/smilies/Drooling.png
dixit/static/images/smilies/Flower.png
dixit/static/images/smilies/Ghost.png
dixit/static/images/smilies/Gift.png
dixit/static/images/smilies/Girl.png
dixit/static/images/smilies/Goodbye.png
dixit/static/images/smilies/Heart.png
dixit/static/images/smilies/Hug.png
dixit/static/images/smilies/Kiss.png
dixit/static/images/smilies/Laughing.png
dixit/static/images/smilies/Lightbulb.png
dixit/static/images/smilies/Loser.png
dixit/static/images/smilies/Love.png
dixit/static/images/smilies/Mail.png
Dixit-0.1.2.dist-info/LICENSE.txt
Dixit-0.1.2.dist-info/METADATA
Dixit-0.1.2.dist-info/WHEEL
Dixit-0.1.2.dist-info/entry_points.txt
Dixit-0.1.2.dist-info/top_level.txt
Dixit-0.1.2.dist-info/RECORD
