Metadata-Version: 2.1
Name: Dixit
Version: 0.1.2
Summary: Fan-created server for the board game Dixit
Home-page: https://github.com/arvoelke/Dixit/
Author: Aaron Voelker
Author-email: arvoelke@gmail.com
License: Free for personal (non-commercial) use
Classifier: Development Status :: 3 - Alpha
Classifier: Topic :: Games/Entertainment :: Board Games
Requires-Python: >=3.5
License-File: LICENSE.txt
Requires-Dist: tornado
Provides-Extra: tests
Requires-Dist: pytest ; extra == 'tests'
